LICENSE.txt
MANIFEST.in
README.rst
requirements-dev.txt
requirements-documentation.txt
requirements-testing.txt
setup.cfg
setup.py
django_simpleimages.egg-info/PKG-INFO
django_simpleimages.egg-info/SOURCES.txt
django_simpleimages.egg-info/dependency_links.txt
django_simpleimages.egg-info/not-zip-safe
django_simpleimages.egg-info/requires.txt
django_simpleimages.egg-info/top_level.txt
docs/source/changelog.rst
docs/source/conf.py
docs/source/configuration.rst
docs/source/contributing.rst
docs/source/index.rst
docs/source/usage.rst
docs/source/why.rst
docs/source/reference/callers.rst
docs/source/reference/index.rst
docs/source/reference/management.commands.retransform.rst
docs/source/reference/trackers.rst
docs/source/reference/transforms.rst
docs/source/reference/utils.rst
simpleimages/__init__.py
simpleimages/callers.py
simpleimages/django_compat.py
simpleimages/models.py
simpleimages/tasks.py
simpleimages/trackers.py
simpleimages/transforms.py
simpleimages/utils.py
simpleimages/management/__init__.py
simpleimages/management/commands/__init__.py
simpleimages/management/commands/retransform.py