Metadata-Version: 1.1
Name: django-simpleimages
Version: 1.3.3
Summary: Opinionated Django image transforms on models
Home-page: https://www.github.com/saulshanabrook/django-simpleimages
Author: Saul Shanabrook
Author-email: s.shanabrook@gmail.com
License: Copyright (c) 2013 Saul Shanabrook
